exception_logger.py
exceptions.py
label_dict.py
preprocess.py
sample.py
source.py
utils.py
sleepology/__init__.py
sleepology/combine.py
sleepology/dataset.py
sleepology/exception_logger.py
sleepology/exceptions.py
sleepology/label_dict.py
sleepology/label_io.py
sleepology/model.py
sleepology/preprocess.py
sleepology/procedure.py
sleepology/sample.py
sleepology/source.py
sleepology/train.py
sleepology/utils.py
sleepology/labeltemplate/aasm.labeltemplate
sleepology-0.2.65.dist-info/LICENSE
sleepology-0.2.65.dist-info/METADATA
sleepology-0.2.65.dist-info/WHEEL
sleepology-0.2.65.dist-info/top_level.txt
sleepology-0.2.65.dist-info/RECORD
